README.rst
setup.cfg
setup.py
biorxiv_cli/__init__.py
biorxiv_cli/api.py
biorxiv_cli/cli.py
biorxiv_cli/config.py
biorxiv_cli/errors.py
biorxiv_cli/utils.py
biorxiv_cli.egg-info/PKG-INFO
biorxiv_cli.egg-info/SOURCES.txt
biorxiv_cli.egg-info/dependency_links.txt
biorxiv_cli.egg-info/entry_points.txt
biorxiv_cli.egg-info/not-zip-safe
biorxiv_cli.egg-info/requires.txt
biorxiv_cli.egg-info/top_level.txt