Metadata-Version: 2.1
Name: biorxiv-cli
Version: 0.1.0
Summary: A Python wrapper for the bioRxiv API.
Home-page: https://github.com/jacquerie/arxiv-cli
Author: Jacopo Notarstefano
Author-email: jacopo.notarstefano@gmail.com
License: MIT
Platform: any
Classifier: Development Status :: 3 - Alpha
Classifier: Environment :: Console
Classifier: Intended Audience :: Developers
Classifier: Intended Audience :: Science/Research
Classifier: License :: OSI Approved :: MIT License
Classifier: Operating System :: OS Independent
Classifier: Programming Language :: Python
Classifier: Programming Language :: Python :: 2
Classifier: Programming Language :: Python :: 2.7
Classifier: Topic :: Scientific/Engineering :: Information Analysis
Classifier: Topic :: Software Development :: Libraries
Classifier: Topic :: Software Development :: Libraries :: Python Modules
Classifier: Topic :: Utilities
Provides-Extra: docs
Provides-Extra: tests
Provides-Extra: all
